{
    "version": "0.15.3",
    "description": "Game Boy and Game Boy Color emulator written in C",
    "homepage": "https://github.com/LIJI32/SameBoy",
    "license": "MIT",
    "url": "https://github.com/LIJI32/SameBoy/releases/download/v0.15.3/sameboy_winsdl_v0.15.3.zip",
    "hash": "df6927d027354fcfbc48a2c0088327c6f1bf751077504d0da22a5bb22b6eb391",
    "bin": "sameboy.exe",
    "shortcuts": [
        [
            "sameboy.exe",
            "SameBoy"
        ]
    ],
    "checkver": "github",
    "autoupdate": {
        "url": "https://github.com/LIJI32/SameBoy/releases/download/v$version/sameboy_winsdl_v$version.zip"
    }
}
