{
    "version": "100.0.4896.62",
    "description": "Chromium without Google components",
    "homepage": "https://github.com/macchrome/winchrome",
    "license": "BSD-3-Clause",
    "architecture": {
        "64bit": {
            "url": "https://github.com/macchrome/winchrome/releases/download/v100.0.4896.62-r972766-Win64/100.0.4896.62_ungoogled_mini_installer.exe#/ungoogled_mini_installer.exe",
            "hash": "27efec6bd28151a1d2b006a5689d27639244617091bb87c813558609c8f43fc0"
        }
    },
    "installer": {
        "args": "--do-not-launch-chrome"
    },
    "uninstaller": {
        "##": "Using 'script' instead of 'file' because it exits with error code 19.",
        "script": "Start-Process -FilePath \"${env:LOCALAPPDATA}\\Chromium\\Application\\$version\\Installer\\setup.exe\" -ArgumentList \"--uninstall --force-uninstall\""
    },
    "checkver": {
        "url": "https://github.com/macchrome/winchrome/releases/latest",
        "regex": "Chromium v(?<version>[\\d.]+)-r(?<rev>[\\d]+) - ungoogled",
        "replace": "${version}"
    },
    "autoupdate": {
        "architecture": {
            "64bit": {
                "url": "https://github.com/macchrome/winchrome/releases/download/v$version-r$matchRev-Win64/$version_ungoogled_mini_installer.exe#/ungoogled_mini_installer.exe"
            }
        }
    }
}
